jp_holiday/__init__.py
jp_holiday/jp_holiday.py
jp_holiday-1.0.4.dist-info/METADATA
jp_holiday-1.0.4.dist-info/WHEEL
jp_holiday-1.0.4.dist-info/top_level.txt
jp_holiday-1.0.4.dist-info/RECORD
