Metadata-Version: 2.1
Name: jp-holiday
Version: 1.0.4
Summary: pandasのデータフレームに日本の日付フラグを与えて，データフレームを返します。
Home-page: https://github.com/kyasby/jp_holiday
Author: kyasby
Author-email: kryo.iryo.tryo@gmail.com
License: MIT
Keywords: holiday japan pandas dataframe
Platform: UNKNOWN
Classifier: License :: OSI Approved :: MIT License
Classifier: Programming Language :: Python :: 3.8
Requires-Dist: jpholiday
